chrov/__init__.py
chrov/_test.py
chrov/annots.py
chrov/core.py
chrov/domains.py
chrov/features.py
chrov/isoforms.py
chrov/run.py
chrov/utils.py
chrov/viz.py
chrov-0.0.4.dist-info/licenses/LICENCE
chrov-0.0.4.dist-info/METADATA
chrov-0.0.4.dist-info/WHEEL
chrov-0.0.4.dist-info/entry_points.txt
chrov-0.0.4.dist-info/top_level.txt
chrov-0.0.4.dist-info/RECORD
