Metadata-Version: 2.4
Name: chrov
Version: 0.0.4
Summary: Chromosome Visualization library in Python.
Home-page: http://github.com/rraadd88/chrov
Author: rraadd88
Author-email: rraadd88 <rohanadandage@gmail.com>
License: General Public License v. 3
Project-URL: Homepage, http://github.com/rraadd88/chrov
Classifier: Programming Language :: Python
Classifier: Programming Language :: Python :: 3
Classifier: Programming Language :: Python :: 3.10
Classifier: Programming Language :: Python :: 3.11
Classifier: Programming Language :: Python :: 3.12
Requires-Python: >=3.7, <4
License-File: LICENCE
Requires-Dist: argh>=0.31.3
Requires-Dist: fastcore==1.7.10
Requires-Dist: matplotlib>=3.10.1
Requires-Dist: nbdev==2.3.31
Requires-Dist: numpy<2
Requires-Dist: pandas>=2
Requires-Dist: pybiomart==0.2.0
Requires-Dist: pyensembl
Requires-Dist: pyranges>=0.1.4
Requires-Dist: roux
Requires-Dist: scipy>=1.15.2
Requires-Dist: seaborn>=0.13.2
Requires-Dist: setuptools>=77.0.3
Dynamic: author
Dynamic: home-page
Dynamic: license-file
Dynamic: requires-python
